[
  {
    "date": "2024-05-30T03:10:50",
    "origin_city": "City_115",
    "destination_city": "City_124",
    "flight_duration_secs": 17614,
    "passengers_on_board": 65
  },
  {
    "date": "2024-05-26T08:13:41",
    "origin_city": "City_115",
    "destination_city": "City_114",
    "flight_duration_secs": 13779,
    "passengers_on_board": 26
  },
  {
    "date": "2024-05-11T20:21:14",
    "origin_city": "City_115",
    "destination_city": "City_82",
    "flight_duration_secs": 6343,
    "passengers_on_board": 289
  },
  {
    "date": "2024-05-06T09:48:28",
    "origin_city": "City_115",
    "destination_city": "City_91",
    "flight_duration_secs": 9007,
    "passengers_on_board": 223
  },
  {
    "date": "2024-05-23T19:35:28",
    "origin_city": "City_115",
    "destination_city": "City_21",
    "flight_duration_secs": 5129,
    "passengers_on_board": 172
  },
  {
    "date": "2024-05-19T09:38:52",
    "origin_city": "City_115",
    "destination_city": "City_36",
    "flight_duration_secs": 17221,
    "passengers_on_board": 110
  },
  {
    "date": "2024-05-28T03:22:55",
    "origin_city": "City_115",
    "destination_city": "City_82",
    "flight_duration_secs": 15387,
    "passengers_on_board": 284
  },
  {
    "date": "2024-05-10T12:36:41",
    "origin_city": "City_115",
    "destination_city": "City_28",
    "flight_duration_secs": 16760,
    "passengers_on_board": 260
  },
  {
    "date": "2024-05-05T14:12:23",
    "origin_city": "City_115",
    "destination_city": "City_107",
    "flight_duration_secs": 14707,
    "passengers_on_board": 287
  },
  {
    "date": "2024-05-26T02:24:23",
    "origin_city": "City_115",
    "destination_city": "City_0",
    "flight_duration_secs": 11108,
    "passengers_on_board": 283
  },
  {
    "date": "2024-05-04T15:27:32",
    "origin_city": "City_115",
    "destination_city": "City_53",
    "flight_duration_secs": 4510,
    "passengers_on_board": 114
  },
  {
    "date": "2024-05-14T19:43:19",
    "origin_city": "City_115",
    "destination_city": "City_13",
    "flight_duration_secs": 15255,
    "passengers_on_board": 94
  },
  {
    "date": "2024-05-27T20:00:30",
    "origin_city": "City_115",
    "destination_city": "City_72",
    "flight_duration_secs": 15495,
    "passengers_on_board": 104
  },
  {
    "date": "2024-05-05T21:51:20",
    "origin_city": "City_115",
    "destination_city": "City_94",
    "flight_duration_secs": 5768,
    "passengers_on_board": 174
  },
  {
    "date": "2024-05-09T06:17:02",
    "origin_city": "City_115",
    "destination_city": "City_59",
    "flight_duration_secs": 9308,
    "passengers_on_board": 195
  },
  {
    "date": "2024-05-04T15:37:22",
    "origin_city": "City_115",
    "destination_city": "City_71",
    "flight_duration_secs": 12488,
    "passengers_on_board": 214
  },
  {
    "date": "2024-05-02T11:30:37",
    "origin_city": "City_115",
    "destination_city": "City_75",
    "flight_duration_secs": 7673,
    "passengers_on_board": 98
  },
  {
    "date": "2024-05-21T04:47:21",
    "origin_city": "City_115",
    "destination_city": "City_31",
    "flight_duration_secs": 9561,
    "passengers_on_board": 84
  },
  {
    "date": "2024-05-08T05:25:56",
    "origin_city": "City_115",
    "destination_city": "City_55",
    "flight_duration_secs": 17985,
    "passengers_on_board": 216
  },
  {
    "date": "2024-05-07T18:20:45",
    "origin_city": "City_115",
    "destination_city": "City_25",
    "flight_duration_secs": 7240,
    "passengers_on_board": 135
  },
  {
    "date": "2024-05-22T05:13:16",
    "origin_city": "City_115",
    "destination_city": "City_24",
    "flight_duration_secs": 9795,
    "passengers_on_board": 234
  },
  {
    "date": "2024-05-27T18:29:32",
    "origin_city": "City_115",
    "destination_city": "City_60",
    "flight_duration_secs": 4599,
    "passengers_on_board": 143
  },
  {
    "date": "2024-05-05T08:58:16",
    "origin_city": "City_115",
    "destination_city": "City_104",
    "flight_duration_secs": 13673,
    "passengers_on_board": 190
  },
  {
    "date": "2024-05-29T07:33:10",
    "origin_city": "City_115",
    "destination_city": "City_3",
    "flight_duration_secs": 16426,
    "passengers_on_board": 1
  },
  {
    "date": "2024-05-13T22:31:00",
    "origin_city": "City_115",
    "destination_city": "City_88",
    "flight_duration_secs": 12031,
    "passengers_on_board": 251
  },
  {
    "date": "2024-05-19T00:18:40",
    "origin_city": "City_115",
    "destination_city": "City_47",
    "flight_duration_secs": 4051,
    "passengers_on_board": 209
  },
  {
    "date": "2024-05-27T13:02:48",
    "origin_city": "City_115",
    "destination_city": "City_119",
    "flight_duration_secs": 15747,
    "passengers_on_board": 135
  },
  {
    "date": "2024-05-26T08:44:13",
    "origin_city": "City_115",
    "destination_city": "City_81",
    "flight_duration_secs": 15902,
    "passengers_on_board": 151
  },
  {
    "date": "2024-05-20T23:41:40",
    "origin_city": "City_115",
    "destination_city": "City_35",
    "flight_duration_secs": 4196,
    "passengers_on_board": 85
  },
  {
    "date": "2024-05-09T13:41:53",
    "origin_city": "City_115",
    "destination_city": "City_56",
    "flight_duration_secs": 8909,
    "passengers_on_board": 262
  },
  {
    "date": "2024-05-04T03:11:59",
    "origin_city": "City_115",
    "destination_city": "City_91",
    "flight_duration_secs": 12791,
    "passengers_on_board": 229
  },
  {
    "date": "2024-05-02T00:33:14",
    "origin_city": "City_115",
    "destination_city": "City_94",
    "flight_duration_secs": 14807,
    "passengers_on_board": 294
  },
  {
    "date": "2024-05-10T01:57:55",
    "origin_city": "City_115",
    "destination_city": "City_18",
    "flight_duration_secs": 17617,
    "passengers_on_board": 251
  },
  {
    "date": "2024-05-17T18:31:32",
    "origin_city": "City_115",
    "destination_city": "City_24",
    "flight_duration_secs": 6432,
    "passengers_on_board": 209
  },
  {
    "date": "2024-05-04T05:40:43",
    "origin_city": "City_115",
    "destination_city": "City_9",
    "flight_duration_secs": 16922,
    "passengers_on_board": 282
  },
  {
    "date": "2024-05-01T23:18:24",
    "origin_city": "City_115",
    "destination_city": "City_81",
    "flight_duration_secs": 12035,
    "passengers_on_board": 247
  },
  {
    "date": "2024-05-21T07:30:17",
    "origin_city": "City_115",
    "destination_city": "City_76",
    "flight_duration_secs": 16748,
    "passengers_on_board": 179
  },
  {
    "date": "2024-05-08T04:51:20",
    "origin_city": "City_115",
    "destination_city": "City_58",
    "flight_duration_secs": 13239,
    "passengers_on_board": 214
  },
  {
    "date": "2024-05-22T12:31:44",
    "origin_city": "City_115",
    "destination_city": "City_81",
    "flight_duration_secs": 15313,
    "passengers_on_board": 55
  },
  {
    "date": "2024-05-14T15:26:04",
    "origin_city": "City_115",
    "destination_city": "City_45",
    "flight_duration_secs": 4087,
    "passengers_on_board": 16
  },
  {
    "date": "2024-05-04T04:46:25",
    "origin_city": "City_115",
    "destination_city": "City_15",
    "flight_duration_secs": 12802,
    "passengers_on_board": 245
  },
  {
    "date": "2024-05-19T03:00:57",
    "origin_city": "City_115",
    "destination_city": "City_39",
    "flight_duration_secs": 8283,
    "passengers_on_board": 268
  },
  {
    "date": "2024-05-02T13:02:09",
    "origin_city": "City_115",
    "destination_city": "City_99",
    "flight_duration_secs": 6942,
    "passengers_on_board": 67
  },
  {
    "date": "2024-05-10T12:57:32",
    "origin_city": "City_115",
    "destination_city": "City_95",
    "flight_duration_secs": 8085,
    "passengers_on_board": 163
  },
  {
    "date": "2024-05-16T06:35:43",
    "origin_city": "City_115",
    "destination_city": "City_46",
    "flight_duration_secs": 14932,
    "passengers_on_board": null
  },
  {
    "date": "2024-05-17T18:26:41",
    "origin_city": "City_115",
    "destination_city": "City_79",
    "flight_duration_secs": 16460,
    "passengers_on_board": 126
  },
  {
    "date": "2024-05-23T05:21:37",
    "origin_city": "City_115",
    "destination_city": "City_7",
    "flight_duration_secs": 16528,
    "passengers_on_board": 81
  },
  {
    "date": "2024-05-10T05:00:56",
    "origin_city": "City_115",
    "destination_city": "City_48",
    "flight_duration_secs": 8473,
    "passengers_on_board": 130
  },
  {
    "date": "2024-05-23T03:41:26",
    "origin_city": "City_115",
    "destination_city": "City_94",
    "flight_duration_secs": 3895,
    "passengers_on_board": 158
  },
  {
    "date": "2024-05-07T09:08:00",
    "origin_city": "City_115",
    "destination_city": "City_4",
    "flight_duration_secs": 13799,
    "passengers_on_board": 184
  },
  {
    "date": "2024-05-17T17:02:02",
    "origin_city": "City_115",
    "destination_city": "City_33",
    "flight_duration_secs": 13131,
    "passengers_on_board": 282
  },
  {
    "date": "2024-05-02T09:39:47",
    "origin_city": "City_115",
    "destination_city": "City_30",
    "flight_duration_secs": 8296,
    "passengers_on_board": 253
  },
  {
    "date": "2024-05-07T04:13:06",
    "origin_city": "City_115",
    "destination_city": "City_89",
    "flight_duration_secs": 7057,
    "passengers_on_board": 219
  },
  {
    "date": "2024-05-01T09:44:16",
    "origin_city": "City_115",
    "destination_city": "City_36",
    "flight_duration_secs": 15792,
    "passengers_on_board": 93
  },
  {
    "date": "2024-05-08T02:06:09",
    "origin_city": "City_115",
    "destination_city": "City_38",
    "flight_duration_secs": 6511,
    "passengers_on_board": 59
  },
  {
    "date": "2024-05-17T05:11:30",
    "origin_city": "City_115",
    "destination_city": "City_105",
    "flight_duration_secs": 17702,
    "passengers_on_board": 112
  },
  {
    "date": "2024-05-28T15:13:43",
    "origin_city": "City_115",
    "destination_city": "City_82",
    "flight_duration_secs": 11461,
    "passengers_on_board": 272
  },
  {
    "date": "2024-05-09T22:06:26",
    "origin_city": "City_115",
    "destination_city": "City_55",
    "flight_duration_secs": 6438,
    "passengers_on_board": 206
  },
  {
    "date": "2024-05-27T03:45:54",
    "origin_city": "City_115",
    "destination_city": "City_53",
    "flight_duration_secs": 4351,
    "passengers_on_board": 162
  },
  {
    "date": "2024-05-29T16:19:10",
    "origin_city": "City_115",
    "destination_city": "City_67",
    "flight_duration_secs": 9371,
    "passengers_on_board": 175
  },
  {
    "date": "2024-05-06T08:42:31",
    "origin_city": "City_115",
    "destination_city": "City_71",
    "flight_duration_secs": 9285,
    "passengers_on_board": 236
  },
  {
    "date": "2024-05-26T13:47:50",
    "origin_city": "City_115",
    "destination_city": "City_31",
    "flight_duration_secs": 12004,
    "passengers_on_board": 283
  },
  {
    "date": "2024-05-05T14:28:28",
    "origin_city": "City_115",
    "destination_city": "City_100",
    "flight_duration_secs": 16226,
    "passengers_on_board": 283
  },
  {
    "date": "2024-05-03T20:31:24",
    "origin_city": "City_115",
    "destination_city": "City_100",
    "flight_duration_secs": 6894,
    "passengers_on_board": 183
  },
  {
    "date": "2024-05-14T19:49:43",
    "origin_city": "City_115",
    "destination_city": "City_18",
    "flight_duration_secs": 16386,
    "passengers_on_board": 233
  },
  {
    "date": "2024-05-07T05:57:23",
    "origin_city": "City_115",
    "destination_city": "City_101",
    "flight_duration_secs": 4124,
    "passengers_on_board": 40
  },
  {
    "date": "2024-05-21T18:36:44",
    "origin_city": "City_115",
    "destination_city": "City_22",
    "flight_duration_secs": 17141,
    "passengers_on_board": 278
  },
  {
    "date": "2024-05-05T22:05:20",
    "origin_city": "City_115",
    "destination_city": "City_30",
    "flight_duration_secs": 11632,
    "passengers_on_board": 259
  },
  {
    "date": "2024-05-07T17:58:27",
    "origin_city": "City_115",
    "destination_city": "City_110",
    "flight_duration_secs": 9431,
    "passengers_on_board": 69
  },
  {
    "date": "2024-05-17T08:09:40",
    "origin_city": "City_115",
    "destination_city": "City_62",
    "flight_duration_secs": 6124,
    "passengers_on_board": 65
  },
  {
    "date": "2024-05-08T04:52:45",
    "origin_city": "City_115",
    "destination_city": "City_52",
    "flight_duration_secs": 14419,
    "passengers_on_board": 20
  },
  {
    "date": "2024-05-15T00:58:31",
    "origin_city": "City_115",
    "destination_city": "City_123",
    "flight_duration_secs": 4995,
    "passengers_on_board": 216
  },
  {
    "date": "2024-05-20T07:07:21",
    "origin_city": "City_115",
    "destination_city": "City_101",
    "flight_duration_secs": 7306,
    "passengers_on_board": 124
  },
  {
    "date": "2024-05-28T20:03:17",
    "origin_city": "City_115",
    "destination_city": "City_16",
    "flight_duration_secs": 16151,
    "passengers_on_board": 210
  },
  {
    "date": "2024-05-24T16:46:58",
    "origin_city": "City_115",
    "destination_city": "City_30",
    "flight_duration_secs": 10765,
    "passengers_on_board": 194
  },
  {
    "date": "2024-05-29T11:55:00",
    "origin_city": "City_115",
    "destination_city": "City_110",
    "flight_duration_secs": 7294,
    "passengers_on_board": 154
  },
  {
    "date": "2024-05-14T01:24:52",
    "origin_city": "City_115",
    "destination_city": "City_68",
    "flight_duration_secs": 17032,
    "passengers_on_board": 207
  },
  {
    "date": "2024-05-27T21:52:23",
    "origin_city": "City_115",
    "destination_city": "City_123",
    "flight_duration_secs": 9165,
    "passengers_on_board": 131
  },
  {
    "date": "2024-05-15T00:28:46",
    "origin_city": "City_115",
    "destination_city": "City_76",
    "flight_duration_secs": 15053,
    "passengers_on_board": 173
  },
  {
    "date": "2024-05-03T12:13:33",
    "origin_city": "City_115",
    "destination_city": "City_77",
    "flight_duration_secs": 15047,
    "passengers_on_board": 131
  },
  {
    "date": "2024-05-15T12:34:35",
    "origin_city": "City_115",
    "destination_city": "City_91",
    "flight_duration_secs": 9624,
    "passengers_on_board": 105
  },
  {
    "date": "2024-05-11T10:45:55",
    "origin_city": "City_115",
    "destination_city": "City_84",
    "flight_duration_secs": 6422,
    "passengers_on_board": 250
  },
  {
    "date": "2024-05-29T11:04:41",
    "origin_city": "City_115",
    "destination_city": "City_51",
    "flight_duration_secs": 11557,
    "passengers_on_board": 95
  }
]